pyChiaLogProcessor.py
pyChiaLogProcessor-0.0.13.dist-info/__pycache__/test_log.cpython-38-pytest-5.4.3.pyc
pyChiaLogProcessor-0.0.13.dist-info/LICENSE.txt
pyChiaLogProcessor-0.0.13.dist-info/METADATA
pyChiaLogProcessor-0.0.13.dist-info/WHEEL
pyChiaLogProcessor-0.0.13.dist-info/top_level.txt
pyChiaLogProcessor-0.0.13.dist-info/RECORD
