Metadata-Version: 2.1
Name: pyChiaLogProcessor
Version: 0.0.13
Summary: Chia plots log porcessor
Home-page: https://github.com/xh-dev-py/xh_py_chia_log_processor
Author: xethhung
Author-email: pypi@xethh.dev
License: UNKNOWN
Platform: UNKNOWN
Provides-Extra: dev
Requires-Dist: pytest (>=3.7) ; extra == 'dev'
